[
	{
		"__TYPE__": "SharedSliceContent",
		"variation": "default",
		"primary": {
			"heading": {
				"__TYPE__": "StructuredTextContent",
				"value": [
					{
						"type": "heading1",
						"content": {
							"text": "Again"
						}
					}
				]
			},
			"image_left": {
				"origin": {
					"id": "main",
					"url": "https://images.unsplash.com/photo-1560762484-813fc97650a0",
					"width": 3344,
					"height": 2509
				},
				"url": "https://images.unsplash.com/photo-1560762484-813fc97650a0",
				"width": 3344,
				"height": 2509,
				"edit": {
					"zoom": 1,
					"crop": {
						"x": 0,
						"y": 0
					},
					"background": "transparent"
				},
				"alt": "straw",
				"credits": null,
				"__TYPE__": "ImageContent",
				"thumbnails": {}
			},
			"image_center": {
				"origin": {
					"id": "main",
					"url": "https://images.unsplash.com/photo-1471897488648-5eae4ac6686b",
					"width": 3560,
					"height": 5340
				},
				"url": "https://images.unsplash.com/photo-1471897488648-5eae4ac6686b",
				"width": 3560,
				"height": 5340,
				"edit": {
					"zoom": 1,
					"crop": {
						"x": 0,
						"y": 0
					},
					"background": "transparent"
				},
				"alt": "deeply",
				"credits": null,
				"__TYPE__": "ImageContent",
				"thumbnails": {}
			},
			"image_right": {
				"origin": {
					"id": "main",
					"url": "https://images.unsplash.com/photo-1587613865763-4b8b0d19e8ab",
					"width": 12288,
					"height": 16384
				},
				"url": "https://images.unsplash.com/photo-1587613865763-4b8b0d19e8ab",
				"width": 12288,
				"height": 16384,
				"edit": {
					"zoom": 1,
					"crop": {
						"x": 0,
						"y": 0
					},
					"background": "transparent"
				},
				"alt": "weigh",
				"credits": null,
				"__TYPE__": "ImageContent",
				"thumbnails": {}
			},
			"body": {
				"__TYPE__": "StructuredTextContent",
				"value": [
					{
						"type": "paragraph",
						"content": {
							"text": "Minim culpa ad sit deserunt laboris culpa. Et officia sunt culpa esse ex magna labore irure aliqua magna in ullamco. Labore velit exercitation laborum sint elit aliqua fugiat anim minim."
						}
					}
				]
			}
		},
		"items": []
	}
]