[
	{
		"__TYPE__": "SharedSliceContent",
		"variation": "default",
		"primary": {
			"heading": {
				"__TYPE__": "StructuredTextContent",
				"value": [
					{
						"type": "heading2",
						"content": {
							"text": "Smoke"
						}
					}
				]
			},
			"body": {
				"__TYPE__": "StructuredTextContent",
				"value": [
					{
						"type": "paragraph",
						"content": {
							"text": "Velit enim qui laborum. Reprehenderit proident laborum dolore dolor veniam labore ipsum labore esse anim eiusmod cupidatat nostrud ullamco consequat."
						}
					}
				]
			},
			"link_left": {
				"key": "4a71df7b-96cf-4d0e-a016-4c9c2ed5d1be",
				"__TYPE__": "LinkContent",
				"value": {
					"__TYPE__": "ExternalLink",
					"url": "https://slicemachine.dev",
					"text": "then"
				}
			},
			"link_right": {
				"key": "abc454c7-fa8a-4290-b248-d1f70520c255",
				"__TYPE__": "LinkContent",
				"value": {
					"__TYPE__": "ExternalLink",
					"url": "http://google.com",
					"text": "worry"
				}
			},
			"background_image": {
				"origin": {
					"id": "main",
					"url": "https://images.unsplash.com/photo-1579931794097-0ad001e51edb",
					"width": 3958,
					"height": 3958
				},
				"url": "https://images.unsplash.com/photo-1579931794097-0ad001e51edb",
				"width": 3958,
				"height": 3958,
				"edit": {
					"zoom": 1,
					"crop": {
						"x": 0,
						"y": 0
					},
					"background": "transparent"
				},
				"alt": "blow",
				"credits": null,
				"__TYPE__": "ImageContent",
				"thumbnails": {}
			}
		},
		"items": []
	}
]