[
	{
		"__TYPE__": "SharedSliceContent",
		"variation": "default",
		"primary": {
			"heading": {
				"__TYPE__": "StructuredTextContent",
				"value": [
					{
						"type": "heading2",
						"content": {
							"text": "Still"
						}
					}
				]
			},
			"services": {
				"__TYPE__": "GroupContentType",
				"value": [
					{
						"__TYPE__": "GroupItemContent",
						"value": [
							[
								"service",
								{
									"key": "b67b77e4-04f4-4b68-aa29-b756c448ac7a",
									"__TYPE__": "LinkContent",
									"value": {
										"__TYPE__": "DocumentLink",
										"id": "mock_document_id"
									}
								}
							]
						]
					}
				]
			}
		},
		"items": []
	}
]